pyoints/__init__.py
pyoints/assertion.py
pyoints/assign.py
pyoints/classification.py
pyoints/clustering.py
pyoints/coords.py
pyoints/distance.py
pyoints/extent.py
pyoints/filters.py
pyoints/fit.py
pyoints/georecords.py
pyoints/indexkd.py
pyoints/interpolate.py
pyoints/misc.py
pyoints/normals.py
pyoints/nptools.py
pyoints/polar.py
pyoints/projection.py
pyoints/smoothing.py
pyoints/surface.py
pyoints/transformation.py
pyoints/vector.py
pyoints/examples/__init__.py
pyoints/examples/base_example.py
pyoints/examples/grid_example.py
pyoints/examples/stemfilter_example.py
pyoints/examples/data/forest.las
pyoints/examples/data/logo_pyoints.jpg
pyoints/examples/file_examples/__init__.py
pyoints/examples/file_examples/csv_example.py
pyoints/examples/file_examples/dump_example.py
pyoints/examples/file_examples/las_example.py
pyoints/examples/file_examples/ply_example.py
pyoints/examples/file_examples/raster_example.py
pyoints/examples/output/.gitignore
pyoints/grid/__init__.py
pyoints/grid/grid.py
pyoints/grid/transformation.py
pyoints/registration/__init__.py
pyoints/registration/icp.py
pyoints/registration/registration.py
pyoints/registration/rototranslations.py
pyoints/storage/BaseGeoHandler.py
pyoints/storage/CsvHandler.py
pyoints/storage/DumpHandler.py
pyoints/storage/LasHandler.py
pyoints/storage/PlyHandler.py
pyoints/storage/RasterHandler.py
pyoints/storage/__init__.py
pyoints/storage/dtype_converters.py
pyoints/storage/misc.py
tests/__init__.py
tests/test_pyoints.py
pyoints-0.2.0a3.dist-info/LICENSE
pyoints-0.2.0a3.dist-info/METADATA
pyoints-0.2.0a3.dist-info/WHEEL
pyoints-0.2.0a3.dist-info/top_level.txt
pyoints-0.2.0a3.dist-info/RECORD
