Metadata-Version: 2.1
Name: pyoints
Version: 0.2.0a3
Summary: A Python package for point cloud, voxel and raster processing.
Home-page: https://laempy.github.io/pyoints/modules.html
Author: Sebastian Lamprecht
Author-email: lamprecht@uni-trier.de
License: GPLv3+
Project-URL: Documentation, https://laempy.github.io/pyoints/modules.html
Project-URL: GitHub, https://github.com/laempy/pyoints
Platform: UNKNOWN
Classifier: Intended Audience :: Science/Research
Classifier: Topic :: Scientific/Engineering :: GIS
Classifier: Topic :: Scientific/Engineering :: Information Analysis
Classifier: Programming Language :: Python :: 3
Classifier: License :: OSI Approved :: GNU General Public License v3 or later (GPLv3+)
Classifier: Operating System :: OS Independent
Classifier: Development Status :: 3 - Alpha
Requires-Python: >=3.5
Requires-Dist: numpy (>=1.15)
Requires-Dist: laspy
Requires-Dist: scipy
Requires-Dist: scikit-learn
Requires-Dist: dill
Requires-Dist: pandas
Requires-Dist: opencv-python
Requires-Dist: plyfile
Requires-Dist: networkx
Requires-Dist: cylinder-fitting
